wpn/__init__.py
wpn-0.2.1.dist-info/METADATA
wpn-0.2.1.dist-info/WHEEL
wpn-0.2.1.dist-info/entry_points.txt
wpn-0.2.1.dist-info/RECORD
