Metadata-Version: 2.4
Name: wpn
Version: 0.2.1
Summary: A Python library for scraping and retrieving song information from the Muzak WPN (What's Playing Now) website. This tool allows you to get current and historical song data for various music channels/stations.
Project-URL: Homepage, https://github.com/lancereinsmith/wpn
Project-URL: Documentation, https://github.com/lancereinsmith/wpn#readme
Project-URL: Repository, https://github.com/lancereinsmith/wpn.git
Project-URL: Issues, https://github.com/lancereinsmith/wpn/issues
Author-email: Lance Reinsmith <info@k2rad.com>
Maintainer-email: Lance Reinsmith <info@k2rad.com>
License: MIT
Keywords: music,muzak,scraping,song,wpn
Classifier: Development Status :: 4 - Beta
Classifier: Intended Audience :: Developers
Classifier: License :: OSI Approved :: MIT License
Classifier: Operating System :: OS Independent
Classifier: Programming Language :: Python :: 3
Classifier: Programming Language :: Python :: 3.12
Classifier: Topic :: Internet :: WWW/HTTP
Classifier: Topic :: Multimedia :: Sound/Audio
Classifier: Topic :: Software Development :: Libraries :: Python Modules
Requires-Python: >=3.12
Requires-Dist: beautifulsoup4>=4.12.0
Requires-Dist: click>=8.1.0
Requires-Dist: grequests>=0.6.0
Requires-Dist: python-levenshtein>=0.21.0
Requires-Dist: requests>=2.31.0
Requires-Dist: thefuzz>=0.19.0
